amical/__init__.py
amical/calibration.py
amical/data_processing.py
amical/dpfit.py
amical/get_infos_obs.py
amical/ifu.py
amical/oifits.py
amical/py.typed
amical/tools.py
amical/_cli/__init__.py
amical/_cli/main.py
amical/_cli/commands/__init__.py
amical/_cli/commands/calibrate.py
amical/_cli/commands/clean.py
amical/_cli/commands/extract.py
amical/analysis/__init__.py
amical/analysis/easy_candid.py
amical/analysis/easy_pymask.py
amical/analysis/fitting.py
amical/analysis/models.py
amical/externals/__init__.py
amical/externals/candid/__init__.py
amical/externals/candid/candid.py
amical/externals/munch/__init__.py
amical/externals/pymask/__init__.py
amical/externals/pymask/cp_tools.py
amical/externals/pymask/cpo.py
amical/externals/pymask/oifits.py
amical/externals/pymask/oitools.py
amical/externals/pymask/pol_tools.py
amical/externals/pymask/x_y_plot.py
amical/internal_data/ifs_wave_YJ.fits
amical/internal_data/ifs_wave_YJH.fits
amical/mf_pipeline/__init__.py
amical/mf_pipeline/ami_function.py
amical/mf_pipeline/bispect.py
amical/mf_pipeline/idl_function.py
amical-1.6.0.dist-info/LICENSE
amical-1.6.0.dist-info/METADATA
amical-1.6.0.dist-info/WHEEL
amical-1.6.0.dist-info/entry_points.txt
amical-1.6.0.dist-info/top_level.txt
amical-1.6.0.dist-info/RECORD
