Metadata-Version: 2.1
Name: amical
Version: 1.6.0
Author-email: Anthony Soulain <anthony.soulain@univ-grenoble-alpes.fr>
License: MIT
Project-URL: Homepage, https://github.com/SydneyAstrophotonicInstrumentationLab/AMICAL
Classifier: Development Status :: 5 - Production/Stable
Classifier: Intended Audience :: Science/Research
Classifier: License :: OSI Approved :: MIT License
Classifier: Operating System :: MacOS :: MacOS X
Classifier: Operating System :: POSIX :: AIX
Classifier: Operating System :: POSIX :: Linux
Classifier: Programming Language :: Python :: 3
Classifier: Programming Language :: Python :: 3 :: Only
Classifier: Topic :: Scientific/Engineering :: Astronomy
Classifier: Typing :: Typed
Requires-Python: >=3.8
License-File: LICENSE
Requires-Dist: astropy (>=5.0)
Requires-Dist: astroquery
Requires-Dist: corner
Requires-Dist: emcee
Requires-Dist: h5py
Requires-Dist: matplotlib
Requires-Dist: numpy
Requires-Dist: pypdf (>=3.2.0)
Requires-Dist: scipy
Requires-Dist: tabulate
Requires-Dist: termcolor
Requires-Dist: tqdm
Requires-Dist: uncertainties
Requires-Dist: importlib-resources (>=1.3) ; python_version < "3.9"
